restful_model/__init__.py
restful_model/context.py
restful_model/database.py
restful_model/utils.py
restful_model/view.py
restful_model-0.1.0.dist-info/METADATA
restful_model-0.1.0.dist-info/RECORD
restful_model-0.1.0.dist-info/WHEEL
restful_model-0.1.0.dist-info/top_level.txt
