Metadata-Version: 2.1
Name: restful-model
Version: 0.1.0
Summary: UNKNOWN
Home-page: https://github.com/zeromake/restful_model
Author: zeromake
Author-email: a390720046@gmail.com
Maintainer: zeromake
Maintainer-email: a390720046@gmail.com
License: MIT
Project-URL: Documentation, restful_model
Requires-Dist: sqlalchemy (>=1.2.9)
